keystone_client/__init__.py
keystone_client/client.py
keystone_client/http.py
keystone_client/log.py
keystone_client/schema.py
keystone_api_client-0.7.0.dist-info/METADATA
keystone_api_client-0.7.0.dist-info/WHEEL
keystone_api_client-0.7.0.dist-info/RECORD
